src/IO/__init__.py
src/IO/fits_table_parser.py
src/IO/hdf5.py
src/IO/lightcurve.py
src/IO/tom_utils.py
src/astrometry/__init__.py
src/astrometry/wcs.py
src/data_quality/__init__.py
src/data_quality/astrometry_qc.py
src/infrastructure/__init__.py
src/infrastructure/aperture_pipeline.py
src/infrastructure/data_classes.py
src/infrastructure/logs.py
src/infrastructure/observations.py
src/infrastructure/time_utils.py
src/logistics/__init__.py
src/logistics/image_tools.py
src/logistics/vizier_tools.py
src/microlensing_photometry/__init__.py
src/microlensing_photometry/example_benchmarks.py
src/microlensing_photometry/example_module.py
src/photometry/__init__.py
src/photometry/aperture_photometry.py
src/photometry/conversions.py
src/photometry/dia_photometry.py
src/photometry/photometric_scale_factor.py
src/photometry/psf.py
src/plots/__init__.py
src/prototypes/__init__.py
src/prototypes/cloud_io_trial.py
src/starfinder/__init__.py
src/starfinder/starfinder.py
src/tools/remove_photometry.py
src/trials/__init__.py
src/trials/amend_phot_tables.py
src/trials/dia_phot_script.py
microlensing_photometry-0.1.0.dist-info/LICENSE
microlensing_photometry-0.1.0.dist-info/METADATA
microlensing_photometry-0.1.0.dist-info/WHEEL
microlensing_photometry-0.1.0.dist-info/entry_points.txt
microlensing_photometry-0.1.0.dist-info/RECORD
