Metadata-Version: 2.3
Name: microlensing_photometry
Version: 0.1.0
Summary: 
License: GNU GENERAL PUBLIC LICENSE
Author: Rachel Street, Etienne Bachelet
Author-email: rstreet@lco.global
Requires-Python: >=3.10
Classifier: Development Status :: 4 - Beta
Classifier: Intended Audience :: Developers
Classifier: Intended Audience :: Science/Research
Classifier: Operating System :: OS Independent
Classifier: Programming Language :: Python
Provides-Extra: dev
Requires-Dist: asv (==0.6.4) ; extra == "dev"
Requires-Dist: jupyter ; extra == "dev"
Requires-Dist: mypy ; extra == "dev"
Requires-Dist: pre-commit ; extra == "dev"
Requires-Dist: pytest ; extra == "dev"
Requires-Dist: pytest-cov ; extra == "dev"
Requires-Dist: ruff ; extra == "dev"
Project-URL: Source Code, https://github.com/LCOGT/microlensing_photometry
